{
  "2.0_2.0": {
    "Expected": [
      {
        "axis": "Attractive",
        "value": 18.333333333333332
      },
      {
        "axis": "Sincere",
        "value": 19.573643410852714
      },
      {
        "axis": "Intelligent",
        "value": 21.372093023255815
      },
      {
        "axis": "Fun",
        "value": 18.06201550387597
      },
      {
        "axis": "Ambitious",
        "value": 12.162790697674419
      }
    ],
    "Perceive": [
      {
        "axis": "Attractive",
        "value": 6.906976744186046
      },
      {
        "axis": "Sincere",
        "value": 7.255813953488372
      },
      {
        "axis": "Intelligent",
        "value": 8.472868217054264
      },
      {
        "axis": "Fun",
        "value": 7.6434108527131785
      },
      {
        "axis": "Ambitious",
        "value": 7.5271317829457365
      }
    ]
  },
  "2.0_4.0": {
    "Expected": [
      {
        "axis": "Attractive",
        "value": 18.56451612903226
      },
      {
        "axis": "Sincere",
        "value": 19.032258064516128
      },
      {
        "axis": "Intelligent",
        "value": 21.016129032258064
      },
      {
        "axis": "Fun",
        "value": 16.370967741935484
      },
      {
        "axis": "Ambitious",
        "value": 11.758064516129032
      }
    ],
    "Perceive": [
      {
        "axis": "Attractive",
        "value": 6.854838709677419
      },
      {
        "axis": "Sincere",
        "value": 7.5
      },
      {
        "axis": "Intelligent",
        "value": 8.693548387096774
      },
      {
        "axis": "Fun",
        "value": 7.225806451612903
      },
      {
        "axis": "Ambitious",
        "value": 7.725806451612903
      }
    ]
  },
  "2.0_3.0": {
    "Expected": [
      {
        "axis": "Attractive",
        "value": 23.571428571428573
      },
      {
        "axis": "Sincere",
        "value": 20.952380952380953
      },
      {
        "axis": "Intelligent",
        "value": 22.61904761904762
      },
      {
        "axis": "Fun",
        "value": 12.80952380952381
      },
      {
        "axis": "Ambitious",
        "value": 10.047619047619047
      }
    ],
    "Perceive": [
      {
        "axis": "Attractive",
        "value": 6.428571428571429
      },
      {
        "axis": "Sincere",
        "value": 7.523809523809524
      },
      {
        "axis": "Intelligent",
        "value": 7.9523809523809526
      },
      {
        "axis": "Fun",
        "value": 7.095238095238095
      },
      {
        "axis": "Ambitious",
        "value": 7.0
      }
    ]
  },
  "2.0_1.0": {
    "Expected": [
      {
        "axis": "Attractive",
        "value": 19.375
      },
      {
        "axis": "Sincere",
        "value": 15.625
      },
      {
        "axis": "Intelligent",
        "value": 16.875
      },
      {
        "axis": "Fun",
        "value": 20.625
      },
      {
        "axis": "Ambitious",
        "value": 14.375
      }
    ],
    "Perceive": [
      {
        "axis": "Attractive",
        "value": 6.875
      },
      {
        "axis": "Sincere",
        "value": 7.375
      },
      {
        "axis": "Intelligent",
        "value": 8.5
      },
      {
        "axis": "Fun",
        "value": 7.25
      },
      {
        "axis": "Ambitious",
        "value": 7.25
      }
    ]
  },
  "2.0_6.0": {
    "Expected": [
      {
        "axis": "Attractive",
        "value": 14.363636363636363
      },
      {
        "axis": "Sincere",
        "value": 29.09090909090909
      },
      {
        "axis": "Intelligent",
        "value": 16.363636363636363
      },
      {
        "axis": "Fun",
        "value": 15.454545454545455
      },
      {
        "axis": "Ambitious",
        "value": 9.090909090909092
      }
    ],
    "Perceive": [
      {
        "axis": "Attractive",
        "value": 6.909090909090909
      },
      {
        "axis": "Sincere",
        "value": 7.545454545454546
      },
      {
        "axis": "Intelligent",
        "value": 8.454545454545455
      },
      {
        "axis": "Fun",
        "value": 7.636363636363637
      },
      {
        "axis": "Ambitious",
        "value": 7.909090909090909
      }
    ]
  },
  "6.0_2.0": {
    "Expected": [
      {
        "axis": "Attractive",
        "value": 16.75
      },
      {
        "axis": "Sincere",
        "value": 18.833333333333332
      },
      {
        "axis": "Intelligent",
        "value": 19.75
      },
      {
        "axis": "Fun",
        "value": 18.583333333333332
      },
      {
        "axis": "Ambitious",
        "value": 17.416666666666668
      }
    ],
    "Perceive": [
      {
        "axis": "Attractive",
        "value": 7.583333333333333
      },
      {
        "axis": "Sincere",
        "value": 8.333333333333334
      },
      {
        "axis": "Intelligent",
        "value": 8.666666666666666
      },
      {
        "axis": "Fun",
        "value": 8.333333333333334
      },
      {
        "axis": "Ambitious",
        "value": 8.5
      }
    ]
  },
  "6.0_4.0": {
    "Expected": [
      {
        "axis": "Attractive",
        "value": 28.0
      },
      {
        "axis": "Sincere",
        "value": 17.615384615384617
      },
      {
        "axis": "Intelligent",
        "value": 16.76923076923077
      },
      {
        "axis": "Fun",
        "value": 15.23076923076923
      },
      {
        "axis": "Ambitious",
        "value": 10.153846153846153
      }
    ],
    "Perceive": [
      {
        "axis": "Attractive",
        "value": 7.846153846153846
      },
      {
        "axis": "Sincere",
        "value": 8.538461538461538
      },
      {
        "axis": "Intelligent",
        "value": 8.692307692307692
      },
      {
        "axis": "Fun",
        "value": 8.153846153846153
      },
      {
        "axis": "Ambitious",
        "value": 8.384615384615385
      }
    ]
  },
  "6.0_3.0": {
    "Expected": [
      {
        "axis": "Attractive",
        "value": 14.285714285714286
      },
      {
        "axis": "Sincere",
        "value": 18.571428571428573
      },
      {
        "axis": "Intelligent",
        "value": 25.714285714285715
      },
      {
        "axis": "Fun",
        "value": 17.142857142857142
      },
      {
        "axis": "Ambitious",
        "value": 8.571428571428571
      }
    ],
    "Perceive": [
      {
        "axis": "Attractive",
        "value": 8.285714285714286
      },
      {
        "axis": "Sincere",
        "value": 9.142857142857142
      },
      {
        "axis": "Intelligent",
        "value": 9.0
      },
      {
        "axis": "Fun",
        "value": 8.857142857142858
      },
      {
        "axis": "Ambitious",
        "value": 9.0
      }
    ]
  },
  "6.0_1.0": {
    "Expected": [
      {
        "axis": "Attractive",
        "value": 18.333333333333332
      },
      {
        "axis": "Sincere",
        "value": 13.333333333333334
      },
      {
        "axis": "Intelligent",
        "value": 15.0
      },
      {
        "axis": "Fun",
        "value": 25.0
      },
      {
        "axis": "Ambitious",
        "value": 13.333333333333334
      }
    ],
    "Perceive": [
      {
        "axis": "Attractive",
        "value": 8.0
      },
      {
        "axis": "Sincere",
        "value": 9.333333333333334
      },
      {
        "axis": "Intelligent",
        "value": 9.333333333333334
      },
      {
        "axis": "Fun",
        "value": 9.0
      },
      {
        "axis": "Ambitious",
        "value": 9.0
      }
    ]
  },
  "6.0_6.0": {
    "Expected": [
      {
        "axis": "Attractive",
        "value": 15.0
      },
      {
        "axis": "Sincere",
        "value": 25.0
      },
      {
        "axis": "Intelligent",
        "value": 15.0
      },
      {
        "axis": "Fun",
        "value": 15.0
      },
      {
        "axis": "Ambitious",
        "value": 15.0
      }
    ],
    "Perceive": [
      {
        "axis": "Attractive",
        "value": 10.0
      },
      {
        "axis": "Sincere",
        "value": 10.0
      },
      {
        "axis": "Intelligent",
        "value": 10.0
      },
      {
        "axis": "Fun",
        "value": 10.0
      },
      {
        "axis": "Ambitious",
        "value": 10.0
      }
    ]
  },
  "3.0_2.0": {
    "Expected": [
      {
        "axis": "Attractive",
        "value": 19.470588235294116
      },
      {
        "axis": "Sincere",
        "value": 18.235294117647058
      },
      {
        "axis": "Intelligent",
        "value": 24.0
      },
      {
        "axis": "Fun",
        "value": 16.352941176470587
      },
      {
        "axis": "Ambitious",
        "value": 12.529411764705882
      }
    ],
    "Perceive": [
      {
        "axis": "Attractive",
        "value": 7.235294117647059
      },
      {
        "axis": "Sincere",
        "value": 7.823529411764706
      },
      {
        "axis": "Intelligent",
        "value": 7.882352941176471
      },
      {
        "axis": "Fun",
        "value": 8.470588235294118
      },
      {
        "axis": "Ambitious",
        "value": 7.352941176470588
      }
    ]
  },
  "3.0_4.0": {
    "Expected": [
      {
        "axis": "Attractive",
        "value": 16.666666666666668
      },
      {
        "axis": "Sincere",
        "value": 18.0
      },
      {
        "axis": "Intelligent",
        "value": 22.166666666666668
      },
      {
        "axis": "Fun",
        "value": 17.166666666666668
      },
      {
        "axis": "Ambitious",
        "value": 11.666666666666666
      }
    ],
    "Perceive": [
      {
        "axis": "Attractive",
        "value": 7.666666666666667
      },
      {
        "axis": "Sincere",
        "value": 7.333333333333333
      },
      {
        "axis": "Intelligent",
        "value": 8.0
      },
      {
        "axis": "Fun",
        "value": 8.666666666666666
      },
      {
        "axis": "Ambitious",
        "value": 7.833333333333333
      }
    ]
  },
  "3.0_3.0": {
    "Expected": [
      {
        "axis": "Attractive",
        "value": 18.75
      },
      {
        "axis": "Sincere",
        "value": 20.0
      },
      {
        "axis": "Intelligent",
        "value": 20.0
      },
      {
        "axis": "Fun",
        "value": 16.25
      },
      {
        "axis": "Ambitious",
        "value": 18.75
      }
    ],
    "Perceive": [
      {
        "axis": "Attractive",
        "value": 7.25
      },
      {
        "axis": "Sincere",
        "value": 8.25
      },
      {
        "axis": "Intelligent",
        "value": 9.0
      },
      {
        "axis": "Fun",
        "value": 8.75
      },
      {
        "axis": "Ambitious",
        "value": 8.75
      }
    ]
  },
  "3.0_1.0": {
    "Expected": [
      {
        "axis": "Attractive",
        "value": 17.5
      },
      {
        "axis": "Sincere",
        "value": 20.0
      },
      {
        "axis": "Intelligent",
        "value": 15.0
      },
      {
        "axis": "Fun",
        "value": 20.0
      },
      {
        "axis": "Ambitious",
        "value": 12.5
      }
    ],
    "Perceive": [
      {
        "axis": "Attractive",
        "value": 7.5
      },
      {
        "axis": "Sincere",
        "value": 9.0
      },
      {
        "axis": "Intelligent",
        "value": 9.0
      },
      {
        "axis": "Fun",
        "value": 8.5
      },
      {
        "axis": "Ambitious",
        "value": 9.0
      }
    ]
  },
  "3.0_6.0": {
    "Expected": [
      {
        "axis": "Attractive",
        "value": 20.0
      },
      {
        "axis": "Sincere",
        "value": 23.333333333333332
      },
      {
        "axis": "Intelligent",
        "value": 16.666666666666668
      },
      {
        "axis": "Fun",
        "value": 13.333333333333334
      },
      {
        "axis": "Ambitious",
        "value": 10.0
      }
    ],
    "Perceive": [
      {
        "axis": "Attractive",
        "value": 7.333333333333333
      },
      {
        "axis": "Sincere",
        "value": 8.0
      },
      {
        "axis": "Intelligent",
        "value": 8.333333333333334
      },
      {
        "axis": "Fun",
        "value": 8.333333333333334
      },
      {
        "axis": "Ambitious",
        "value": 8.0
      }
    ]
  },
  "1.0_2.0": {
    "Expected": [
      {
        "axis": "Attractive",
        "value": 16.0
      },
      {
        "axis": "Sincere",
        "value": 20.0
      },
      {
        "axis": "Intelligent",
        "value": 25.0
      },
      {
        "axis": "Fun",
        "value": 18.0
      },
      {
        "axis": "Ambitious",
        "value": 9.0
      }
    ],
    "Perceive": [
      {
        "axis": "Attractive",
        "value": 7.6
      },
      {
        "axis": "Sincere",
        "value": 8.8
      },
      {
        "axis": "Intelligent",
        "value": 9.0
      },
      {
        "axis": "Fun",
        "value": 6.6
      },
      {
        "axis": "Ambitious",
        "value": 8.0
      }
    ]
  },
  "1.0_4.0": {
    "Expected": [
      {
        "axis": "Attractive",
        "value": 25.6
      },
      {
        "axis": "Sincere",
        "value": 15.2
      },
      {
        "axis": "Intelligent",
        "value": 17.2
      },
      {
        "axis": "Fun",
        "value": 16.2
      },
      {
        "axis": "Ambitious",
        "value": 10.8
      }
    ],
    "Perceive": [
      {
        "axis": "Attractive",
        "value": 7.0
      },
      {
        "axis": "Sincere",
        "value": 9.4
      },
      {
        "axis": "Intelligent",
        "value": 8.8
      },
      {
        "axis": "Fun",
        "value": 7.2
      },
      {
        "axis": "Ambitious",
        "value": 8.2
      }
    ]
  },
  "1.0_3.0": {
    "Expected": [
      {
        "axis": "Attractive",
        "value": 30.0
      },
      {
        "axis": "Sincere",
        "value": 20.0
      },
      {
        "axis": "Intelligent",
        "value": 20.0
      },
      {
        "axis": "Fun",
        "value": 10.0
      },
      {
        "axis": "Ambitious",
        "value": 15.0
      }
    ],
    "Perceive": [
      {
        "axis": "Attractive",
        "value": 10.0
      },
      {
        "axis": "Sincere",
        "value": 7.0
      },
      {
        "axis": "Intelligent",
        "value": 10.0
      },
      {
        "axis": "Fun",
        "value": 6.0
      },
      {
        "axis": "Ambitious",
        "value": 9.0
      }
    ]
  },
  "1.0_1.0": {
    "Expected": [
      {
        "axis": "Attractive",
        "value": 20.0
      },
      {
        "axis": "Sincere",
        "value": 20.0
      },
      {
        "axis": "Intelligent",
        "value": 20.0
      },
      {
        "axis": "Fun",
        "value": 10.0
      },
      {
        "axis": "Ambitious",
        "value": 20.0
      }
    ],
    "Perceive": [
      {
        "axis": "Attractive",
        "value": 8.5
      },
      {
        "axis": "Sincere",
        "value": 8.5
      },
      {
        "axis": "Intelligent",
        "value": 9.5
      },
      {
        "axis": "Fun",
        "value": 7.5
      },
      {
        "axis": "Ambitious",
        "value": 9.5
      }
    ]
  },
  "1.0_6.0": {
    "Expected": [
      {
        "axis": "Attractive",
        "value": 7.0
      },
      {
        "axis": "Sincere",
        "value": 35.0
      },
      {
        "axis": "Intelligent",
        "value": 20.0
      },
      {
        "axis": "Fun",
        "value": 20.0
      },
      {
        "axis": "Ambitious",
        "value": 5.0
      }
    ],
    "Perceive": [
      {
        "axis": "Attractive",
        "value": 8.5
      },
      {
        "axis": "Sincere",
        "value": 8.5
      },
      {
        "axis": "Intelligent",
        "value": 9.5
      },
      {
        "axis": "Fun",
        "value": 7.5
      },
      {
        "axis": "Ambitious",
        "value": 9.5
      }
    ]
  },
  "4.0_2.0": {
    "Expected": [
      {
        "axis": "Attractive",
        "value": 20.136363636363637
      },
      {
        "axis": "Sincere",
        "value": 18.5
      },
      {
        "axis": "Intelligent",
        "value": 22.59090909090909
      },
      {
        "axis": "Fun",
        "value": 17.454545454545453
      },
      {
        "axis": "Ambitious",
        "value": 9.954545454545455
      }
    ],
    "Perceive": [
      {
        "axis": "Attractive",
        "value": 6.0
      },
      {
        "axis": "Sincere",
        "value": 7.863636363636363
      },
      {
        "axis": "Intelligent",
        "value": 7.954545454545454
      },
      {
        "axis": "Fun",
        "value": 6.909090909090909
      },
      {
        "axis": "Ambitious",
        "value": 7.636363636363637
      }
    ]
  },
  "4.0_4.0": {
    "Expected": [
      {
        "axis": "Attractive",
        "value": 19.68
      },
      {
        "axis": "Sincere",
        "value": 18.0
      },
      {
        "axis": "Intelligent",
        "value": 20.88
      },
      {
        "axis": "Fun",
        "value": 18.76
      },
      {
        "axis": "Ambitious",
        "value": 10.2
      }
    ],
    "Perceive": [
      {
        "axis": "Attractive",
        "value": 6.32
      },
      {
        "axis": "Sincere",
        "value": 8.72
      },
      {
        "axis": "Intelligent",
        "value": 8.36
      },
      {
        "axis": "Fun",
        "value": 7.56
      },
      {
        "axis": "Ambitious",
        "value": 7.48
      }
    ]
  },
  "4.0_3.0": {
    "Expected": [
      {
        "axis": "Attractive",
        "value": 13.75
      },
      {
        "axis": "Sincere",
        "value": 17.5
      },
      {
        "axis": "Intelligent",
        "value": 22.5
      },
      {
        "axis": "Fun",
        "value": 18.75
      },
      {
        "axis": "Ambitious",
        "value": 17.5
      }
    ],
    "Perceive": [
      {
        "axis": "Attractive",
        "value": 6.25
      },
      {
        "axis": "Sincere",
        "value": 7.5
      },
      {
        "axis": "Intelligent",
        "value": 7.75
      },
      {
        "axis": "Fun",
        "value": 8.0
      },
      {
        "axis": "Ambitious",
        "value": 8.0
      }
    ]
  },
  "4.0_1.0": {
    "Expected": [
      {
        "axis": "Attractive",
        "value": 16.666666666666668
      },
      {
        "axis": "Sincere",
        "value": 18.333333333333332
      },
      {
        "axis": "Intelligent",
        "value": 25.0
      },
      {
        "axis": "Fun",
        "value": 13.333333333333334
      },
      {
        "axis": "Ambitious",
        "value": 15.0
      }
    ],
    "Perceive": [
      {
        "axis": "Attractive",
        "value": 5.333333333333333
      },
      {
        "axis": "Sincere",
        "value": 8.0
      },
      {
        "axis": "Intelligent",
        "value": 8.0
      },
      {
        "axis": "Fun",
        "value": 7.666666666666667
      },
      {
        "axis": "Ambitious",
        "value": 8.0
      }
    ]
  },
  "4.0_6.0": {
    "Expected": [
      {
        "axis": "Attractive",
        "value": 13.5
      },
      {
        "axis": "Sincere",
        "value": 27.5
      },
      {
        "axis": "Intelligent",
        "value": 20.0
      },
      {
        "axis": "Fun",
        "value": 15.0
      },
      {
        "axis": "Ambitious",
        "value": 7.5
      }
    ],
    "Perceive": [
      {
        "axis": "Attractive",
        "value": 7.0
      },
      {
        "axis": "Sincere",
        "value": 8.0
      },
      {
        "axis": "Intelligent",
        "value": 7.5
      },
      {
        "axis": "Fun",
        "value": 7.0
      },
      {
        "axis": "Ambitious",
        "value": 6.5
      }
    ]
  }
}